arca/__init__.py
arca/_arca.py
arca/_runner.py
arca/exceptions.py
arca/result.py
arca/task.py
arca/utils.py
arca/backend/__init__.py
arca/backend/base.py
arca/backend/current_environment.py
arca/backend/docker.py
arca/backend/vagrant.py
arca/backend/venv.py
arca-0.3.3.dist-info/LICENSE
arca-0.3.3.dist-info/METADATA
arca-0.3.3.dist-info/WHEEL
arca-0.3.3.dist-info/top_level.txt
arca-0.3.3.dist-info/RECORD
