Metadata-Version: 2.1
Name: arca
Version: 0.3.3
Summary: A library for running Python functions (callables) from git repositories in various states of isolation with integrating caching.
Home-page: https://github.com/pyvec/arca
Author: Mikuláš Poul
Author-email: mikulaspoul@gmail.com
License: MIT
Project-URL: Documentation, https://arca.readthedocs.io/
Project-URL: CI, https://travis-ci.org/pyvec/arca
Project-URL: Test coverage, https://codecov.io/gh/pyvec/arca
Keywords: sandboxing,git,docker,vagrant
Platform: UNKNOWN
Classifier: Development Status :: 4 - Beta
Classifier: Intended Audience :: Developers
Classifier: License :: OSI Approved :: MIT License
Classifier: Programming Language :: Python
Classifier: Programming Language :: Python :: 3
Classifier: Programming Language :: Python :: 3 :: Only
Classifier: Programming Language :: Python :: 3.6
Classifier: Programming Language :: Python :: 3.7
Classifier: Programming Language :: Python :: 3.8
Classifier: Topic :: Security
Classifier: Topic :: Utilities
Classifier: Topic :: Software Development :: Build Tools
Classifier: Topic :: Software Development :: Version Control :: Git
Requires-Dist: gitpython (~=3.0.5)
Requires-Dist: dogpile.cache (~=0.9.0)
Requires-Dist: requests
Requires-Dist: entrypoints (>=0.2.3)
Requires-Dist: cached-property
Provides-Extra: docker
Requires-Dist: docker (~=3.2.1) ; extra == 'docker'
Provides-Extra: vagrant
Requires-Dist: docker (~=3.2.1) ; extra == 'vagrant'
Requires-Dist: python-vagrant ; extra == 'vagrant'
Requires-Dist: fabric3 ; extra == 'vagrant'
